LICENCE.txt
MANIFEST.in
README.txt
setup.py
ezAdmin/__init__.py
ezAdmin.egg-info/PKG-INFO
ezAdmin.egg-info/SOURCES.txt
ezAdmin.egg-info/dependency_links.txt
ezAdmin.egg-info/top_level.txt