Metadata-Version: 2.1
Name: ezAdmin
Version: 0.0.1
Summary: An easier way of PYUAC module
Home-page: 
Author: EzGame Guy
Author-email: lephuchung9267@gmail.com
License: MIT
Keywords: ezAdmin
Classifier: Development Status :: 5 - Production/Stable
Classifier: Intended Audience :: Education
Classifier: Operating System :: Microsoft :: Windows :: Windows 10
Classifier: License :: OSI Approved :: MIT License
Classifier: Programming Language :: Python :: 3
License-File: LICENCE.txt
